cuss_inspect/__init__.py
cuss_inspect/cuss_inspect.py
cuss_inspect/data/logitclf_v4.lgst
cuss_inspect/data/vectorizer_v4.lgst
cuss_inspect-1.0.2b0.dist-info/LICENSE
cuss_inspect-1.0.2b0.dist-info/METADATA
cuss_inspect-1.0.2b0.dist-info/WHEEL
cuss_inspect-1.0.2b0.dist-info/top_level.txt
cuss_inspect-1.0.2b0.dist-info/RECORD
