Metadata-Version: 2.1
Name: cuss-inspect
Version: 1.0.2b0
Summary: A basic and simple yet powerful Python library to detect toxicity/profanity of a review or list of reveiws.
Home-page: https://github.com/tushar50896/cuss_inspect
Author: Tushar, Lalit, Gurwinder
Author-email: tushar50896@gmail.com, lalitsharma2395@gmail.com,sgurwinderr@gmail.com
License: UNKNOWN
Platform: UNKNOWN
Classifier: Development Status :: 4 - Beta
Classifier: Natural Language :: English
Classifier: Programming Language :: Python :: 3
Classifier: Programming Language :: Python :: 3.6
Classifier: Programming Language :: Python :: 3.7
Classifier: Programming Language :: Python :: 3.8
Classifier: License :: OSI Approved :: MIT License
Classifier: Operating System :: OS Independent
Classifier: Topic :: Scientific/Engineering :: Artificial Intelligence
Requires-Python: >=3.6
Requires-Dist: scikit-learn (>=0.23.2)
Requires-Dist: pandas (>=1.1.3)
Requires-Dist: numpy (>=1.19.2)
